plone.memoize-3.0.4-py3.13-nspkg.pth
plone/memoize/README.rst
plone/memoize/__init__.py
plone/memoize/compress.py
plone/memoize/compress.rst
plone/memoize/configure.zcml
plone/memoize/forever.py
plone/memoize/forever.rst
plone/memoize/instance.py
plone/memoize/instance.rst
plone/memoize/interfaces.py
plone/memoize/ram.py
plone/memoize/ram.rst
plone/memoize/request.py
plone/memoize/request.rst
plone/memoize/tests.py
plone/memoize/view.py
plone/memoize/view.rst
plone/memoize/volatile.py
plone/memoize/volatile.rst
plone_memoize-3.0.4.dist-info/METADATA
plone_memoize-3.0.4.dist-info/WHEEL
plone_memoize-3.0.4.dist-info/namespace_packages.txt
plone_memoize-3.0.4.dist-info/top_level.txt
plone_memoize-3.0.4.dist-info/RECORD
